kisseru/__init__.py
kisseru/backend.py
kisseru/bash.py
kisseru/builtins.py
kisseru/colors.py
kisseru/dot.py
kisseru/func.py
kisseru/fusion.py
kisseru/handler.py
kisseru/ir.py
kisseru/kisseru-cli.py
kisseru/kisseru.py
kisseru/local.py
kisseru/logger.py
kisseru/passes.py
kisseru/process.py
kisseru/profiler.py
kisseru/slurm.py
kisseru/stage.py
kisseru/tasks.py
kisseru/tracer.py
kisseru/transform.py
kisseru/typed.py
kisseru/utils.py
kisseru-0.2.4.data/scripts/kisseru-cli
kisseru-0.2.4.dist-info/LICENCE
kisseru-0.2.4.dist-info/METADATA
kisseru-0.2.4.dist-info/WHEEL
kisseru-0.2.4.dist-info/top_level.txt
kisseru-0.2.4.dist-info/RECORD
