Metadata-Version: 2.1
Name: kisseru
Version: 0.2.4
Summary: A simply scriptable workflow library for data pipelines.
Home-page: https://github.com/chamibuddhika/kisseru
Author: Buddhika Chamith
Author-email: chamibuddhika@gmail.com
License: UNKNOWN
Platform: UNKNOWN
Classifier: Programming Language :: Python :: 3
Classifier: License :: OSI Approved :: Apache Software License
Classifier: Operating System :: OS Independent
Requires-Dist: pandas
Requires-Dist: xlwt
Requires-Dist: xlrd
Requires-Dist: numpy
Requires-Dist: jsonpickle
Requires-Dist: click
